punppci/__init__.py
punppci/benchmark.py
punppci/dataset.py
punppci/example.py
punppci/model.py
punppci/networks.py
punppci/optimizer.py
punppci/plot.py
punppci/models/__init__.py
punppci/models/chain_ladder.py
punppci/models/ppci.py
punppci/models/punppci.py
punppci-0.0.8.dist-info/LICENSE
punppci-0.0.8.dist-info/METADATA
punppci-0.0.8.dist-info/WHEEL
punppci-0.0.8.dist-info/top_level.txt
punppci-0.0.8.dist-info/RECORD
