Metadata-Version: 2.1
Name: punppci
Version: 0.0.8
Summary: Neural network for insurance claims modelling
Home-page: https://github.com/JackyP/penalised-unexplainability-network-payments-per-claim-incurred
Author: Jacky Poon
Author-email: jackypn@gmail.com
License: UNKNOWN
Platform: UNKNOWN
Classifier: Programming Language :: Python :: 3
Classifier: License :: OSI Approved :: GNU General Public License v3 or later (GPLv3+)
Classifier: Operating System :: OS Independent
Requires-Dist: pandas (>=0.24.1)
Requires-Dist: koalas (>=0.4.0)
Requires-Dist: numpy (>=1.14.2)
Requires-Dist: scikit-learn (>=0.20.3)
Requires-Dist: PDPbox (>=0.2.0)
Requires-Dist: ipython (>=6.4.0)
Requires-Dist: scikit-optimize (>=0.5.2)
Requires-Dist: python-dateutil (>=2.7.3)
Requires-Dist: torch (>=1.1.0)
Requires-Dist: hiddenlayer (>=0.2)
Requires-Dist: graphviz (>=0.10.1)
Requires-Dist: skorch (>=0.5.0)
